deadpipe/__init__.py
deadpipe-4.0.0.dist-info/METADATA
deadpipe-4.0.0.dist-info/WHEEL
deadpipe-4.0.0.dist-info/licenses/LICENSE
deadpipe-4.0.0.dist-info/RECORD
