Metadata-Version: 2.4
Name: deadpipe
Version: 4.0.0
Summary: LLM observability that answers: Is this prompt still behaving safely?
Project-URL: Homepage, https://deadpipe.com
Project-URL: Documentation, https://deadpipe.com/docs
Project-URL: Repository, https://github.com/deadpipe/deadpipe-python
Author-email: Deadpipe <hello@deadpipe.com>
Maintainer-email: Deadpipe <hello@deadpipe.com>
License-File: LICENSE
Keywords: ai,anthropic,claude,cohere,gemini,google-ai,gpt,llm,machine-learning,mistral,monitoring,observability,openai,prompt-tracking,telemetry
Classifier: Development Status :: 4 - Beta
Classifier: Intended Audience :: Developers
Classifier: Operating System :: OS Independent
Classifier: Programming Language :: Python :: 3
Classifier: Programming Language :: Python :: 3.8
Classifier: Programming Language :: Python :: 3.9
Classifier: Programming Language :: Python :: 3.10
Classifier: Programming Language :: Python :: 3.11
Classifier: Programming Language :: Python :: 3.12
Classifier: Topic :: Scientific/Engineering :: Artificial Intelligence
Classifier: Topic :: System :: Monitoring
Requires-Python: >=3.8
Provides-Extra: pydantic
Requires-Dist: pydantic>=2.0.0; extra == 'pydantic'
